articlay.py
articlay-1.1.6.dist-info/licenses/LICENSE
articlay-1.1.6.dist-info/METADATA
articlay-1.1.6.dist-info/WHEEL
articlay-1.1.6.dist-info/entry_points.txt
articlay-1.1.6.dist-info/top_level.txt
articlay-1.1.6.dist-info/RECORD
